keith3390/__init__.py
keith3390/_version.py
keith3390/main.py
keith3390/siggen.py
keith3390_ioc-0.5.1.dist-info/LICENSE
keith3390_ioc-0.5.1.dist-info/METADATA
keith3390_ioc-0.5.1.dist-info/WHEEL
keith3390_ioc-0.5.1.dist-info/entry_points.txt
keith3390_ioc-0.5.1.dist-info/top_level.txt
keith3390_ioc-0.5.1.dist-info/RECORD
