Metadata-Version: 2.1
Name: keith3390-ioc
Version: 0.5.1
Summary: EMMI-based IOC for the Keithley 3390 signal generator
Author-email: Florin Boariu <florin.pt@rootshell.ro>, Matthias Rössle <matthias.roessle@helmholtz-berlin.de>
Project-URL: Source Code, https://gitlab.com/kmc3-xpp/keith3390-ioc/
Project-URL: Bug Tracker, https://gitlab.com/kmc3-xpp/keith3390-ioc/-/issues
Classifier: Programming Language :: Python :: 3
Classifier: License :: OSI Approved :: GNU General Public License v3 or later (GPLv3+)
Classifier: Operating System :: POSIX :: Linux
Classifier: Development Status :: 2 - Pre-Alpha
Classifier: Environment :: Console
Classifier: Intended Audience :: Science/Research
Classifier: Topic :: Scientific/Engineering
Requires-Python: >=3.8
License-File: LICENSE
Requires-Dist: emmi[scpi,softioc] >=0.6.0
Requires-Dist: emmi-escpi
Requires-Dist: opentelemetry-api
Requires-Dist: opentelemetry-exporter-otlp
Requires-Dist: numpy
Requires-Dist: scipy
Provides-Extra: test
Requires-Dist: pytest ; extra == 'test'
Requires-Dist: pytest-cov ; extra == 'test'
Requires-Dist: pytest-asyncio ; extra == 'test'
